dynu_renew/__init__.py
dynu_renew/__main__.py
dynu_renew/database.py
dynu_renew-1.0.3.dist-info/LICENSE
dynu_renew-1.0.3.dist-info/METADATA
dynu_renew-1.0.3.dist-info/WHEEL
dynu_renew-1.0.3.dist-info/RECORD
