Metadata-Version: 2.1
Name: dynu-renew
Version: 1.0.3
Summary: A Python module to renew public IP address associated with a Dynu domain.
Author: Simone Perini
Author-email: 39993316+CoffeePerry@users.noreply.github.com
Requires-Python: >=3.10,<4.0
Classifier: Programming Language :: Python :: 3
Classifier: Programming Language :: Python :: 3.10
Classifier: Programming Language :: Python :: 3.11
Requires-Dist: ipify-py (>=1.0.1,<2.0.0)
Requires-Dist: requests (>=2.31.0,<3.0.0)
